objecttools
