Metadata-Version: 1.1
Name: objecttools
Version: 1.0.1
Summary: Various tools for working with objects and classes in Python
Home-page: https://github.com/MitalAshok/objecttools
Author: Mital Ashok
Author-email: mital.vaja@googlemail.com
License: MIT
Keywords: library,cached,properties,singletons
Platform: any
Classifier: Development Status :: 5 - Production/Stable
Classifier: Intended Audience :: Developers
Classifier: License :: OSI Approved :: MIT License
Classifier: Operating System :: OS Independent
Classifier: Programming Language :: Python :: 2
Classifier: Programming Language :: Python :: 2.7
Classifier: Programming Language :: Python :: 3
Classifier: Programming Language :: Python :: 3.4
Classifier: Programming Language :: Python :: 3.5
Classifier: Programming Language :: Python :: 3.6
Classifier: Topic :: Software Development :: Libraries
